[{"word":"Ewe","type":"n.","descr":" The female of the sheep, and of sheeplike animals."},{"word":"Ewe-necked","type":"a.","descr":" Having a neck like a ewe; -- said of horses in which the arch of the neck is deficent, being somewhat hollowed out."},{"word":"Ewer","type":"n.","descr":" A kind of widemouthed pitcher or jug; esp., one used to hold water for the toilet."},{"word":"Ewery","type":"n.","descr":" Alt. of Ewry"},{"word":"Ewry","type":"n.","descr":" An office or place of household service where the ewers were formerly kept."},{"word":"Ewt","type":"n.","descr":" The newt."}]